slcs/__init__.py
slcs/_modidx.py
slcs/atyp.py
slcs/cons.py
slcs/core.py
slcs/dcls.py
slcs/mskr.py
slcs/slcr.py
slcs/tens.py
slcs/util.py
slcs-0.0.2.dist-info/LICENSE
slcs-0.0.2.dist-info/METADATA
slcs-0.0.2.dist-info/WHEEL
slcs-0.0.2.dist-info/entry_points.txt
slcs-0.0.2.dist-info/top_level.txt
slcs-0.0.2.dist-info/RECORD
